odoo/addons/purchase_representative/README.rst
odoo/addons/purchase_representative/__init__.py
odoo/addons/purchase_representative/__manifest__.py
odoo/addons/purchase_representative/hooks.py
odoo/addons/purchase_representative/i18n/purchase_representative.pot
odoo/addons/purchase_representative/models/__init__.py
odoo/addons/purchase_representative/models/procurement_rule.py
odoo/addons/purchase_representative/models/purchase_order.py
odoo/addons/purchase_representative/readme/CONTRIBUTORS.rst
odoo/addons/purchase_representative/readme/DESCRIPTION.rst
odoo/addons/purchase_representative/readme/ROADMAP.rst
odoo/addons/purchase_representative/readme/USAGE.rst
odoo/addons/purchase_representative/static/description/icon.png
odoo/addons/purchase_representative/static/description/index.html
odoo/addons/purchase_representative/views/purchase_order_view.xml
odoo11_addon_purchase_representative-11.0.1.0.0.99.dev3.dist-info/METADATA
odoo11_addon_purchase_representative-11.0.1.0.0.99.dev3.dist-info/WHEEL
odoo11_addon_purchase_representative-11.0.1.0.0.99.dev3.dist-info/top_level.txt
odoo11_addon_purchase_representative-11.0.1.0.0.99.dev3.dist-info/RECORD
